yookassa_telegram/__init__.py
yookassa_telegram/config.py
yookassa_telegram/database_storage.py
yookassa_telegram/enums.py
yookassa_telegram/exceptions.py
yookassa_telegram/models.py
yookassa_telegram/payment_expiration.py
yookassa_telegram/payment_service.py
yookassa_telegram/receipt_service.py
yookassa_telegram/refund_service.py
yookassa_telegram/storage.py
yookassa_telegram/telegram_integration.py
yookassa_telegram/utils.py
yookassa_telegram/webhook_handler.py
yookassa_telegram/webhook_order_integration.py
yookassa_telegram/yookassa_client.py
yookassa_telegram-1.2.0.dist-info/licenses/LICENSE
yookassa_telegram-1.2.0.dist-info/METADATA
yookassa_telegram-1.2.0.dist-info/WHEEL
yookassa_telegram-1.2.0.dist-info/top_level.txt
yookassa_telegram-1.2.0.dist-info/RECORD
