Metadata-Version: 2.4
Name: yookassa-telegram
Version: 1.2.0
Summary: By @rerowros
Author-email: rerowros <rerowros@gmail.com>
License: MIT
Project-URL: Homepage, https://github.com/Rerowros/yookassa-telegram
Project-URL: Documentation, https://github.com/Rerowros/yookassa-telegram#readme
Project-URL: Repository, https://github.com/Rerowros/yookassa-telegram
Project-URL: Issues, https://github.com/Rerowros/yookassa-telegram/issues
Keywords: yookassa,telegram,bot,payment,aiogram
Classifier: Development Status :: 4 - Beta
Classifier: Intended Audience :: Developers
Classifier: License :: OSI Approved :: MIT License
Classifier: Programming Language :: Python :: 3
Classifier: Programming Language :: Python :: 3.10
Classifier: Programming Language :: Python :: 3.11
Classifier: Programming Language :: Python :: 3.12
Classifier: Topic :: Software Development :: Libraries :: Python Modules
Requires-Python: >=3.10
License-File: LICENSE
Requires-Dist: aiogram>=3.0.0
Requires-Dist: aiohttp>=3.8.0
Requires-Dist: yookassa>=2.0.0
Provides-Extra: dev
Requires-Dist: pytest>=7.0.0; extra == "dev"
Requires-Dist: pytest-asyncio>=0.21.0; extra == "dev"
Requires-Dist: black>=23.0.0; extra == "dev"
Requires-Dist: mypy>=1.0.0; extra == "dev"
Dynamic: license-file
